georouting/__init__.py
georouting/cli.py
georouting/georouting.py
georouting/utils.py
georouting/routers/__init__.py
georouting/routers/baidu.py
georouting/routers/base.py
georouting/routers/bing.py
georouting/routers/esri.py
georouting/routers/google.py
georouting/routers/osmnx.py
georouting/routers/osrm.py
georouting-0.0.8.dist-info/AUTHORS.rst
georouting-0.0.8.dist-info/LICENSE
georouting-0.0.8.dist-info/METADATA
georouting-0.0.8.dist-info/WHEEL
georouting-0.0.8.dist-info/dependency_links.txt
georouting-0.0.8.dist-info/entry_points.txt
georouting-0.0.8.dist-info/top_level.txt
georouting-0.0.8.dist-info/RECORD
