Metadata-Version: 2.1
Name: georouting
Version: 0.0.8
Summary: Geo routing for Python users
Home-page: https://github.com/wybert/georouting
Author: Xiaokang Fu
Author-email: fxk123@gmail.com
License: MIT license
Keywords: georouting
Classifier: Development Status :: 2 - Pre-Alpha
Classifier: Intended Audience :: Developers
Classifier: License :: OSI Approved :: MIT License
Classifier: Natural Language :: English
Classifier: Programming Language :: Python :: 3
Classifier: Programming Language :: Python :: 3.7
Classifier: Programming Language :: Python :: 3.8
Classifier: Programming Language :: Python :: 3.9
Classifier: Programming Language :: Python :: 3.10
Requires-Python: >=3.7
License-File: LICENSE
License-File: AUTHORS.rst
Requires-Dist: igraph
Requires-Dist: osmnx
Requires-Dist: polyline
Requires-Dist: googlemaps
Requires-Dist: geopandas
Requires-Dist: folium
Requires-Dist: mapclassify
Requires-Dist: matplotlib
